README.md
setup.py
snsdl/__init__.py
snsdl.egg-info/PKG-INFO
snsdl.egg-info/SOURCES.txt
snsdl.egg-info/dependency_links.txt
snsdl.egg-info/not-zip-safe
snsdl.egg-info/top_level.txt
snsdl/evaluation/__init__.py
snsdl/evaluation/eval.py
snsdl/io/__init__.py
snsdl/io/hdf5/__init__.py
snsdl/io/hdf5/base_writer.py
snsdl/io/hdf5/writer.py
snsdl/io/hdf5/utils/__init__.py
snsdl/io/hdf5/utils/trainingds.py
snsdl/keras/__init__.py
snsdl/keras/generators/__init__.py
snsdl/keras/generators/img_fs_batch_generator.py
snsdl/keras/generators/txt_file_batch_generator.py
snsdl/keras/generators/base/__init__.py
snsdl/keras/generators/base/base_sequence_generator.py
snsdl/keras/generators/base/img_fs_sequence_generator.py
snsdl/keras/generators/base/txt_file_sequence_generator.py
snsdl/keras/wrappers/__init__.py
snsdl/keras/wrappers/base_model.py
snsdl/keras/wrappers/base_wrapper.py
snsdl/keras/wrappers/mlflow_classifier.py
snsdl/utils/__init__.py
snsdl/utils/paths.py
snsdl/utils/splitds.py