Metadata-Version: 1.0
Name: snsdl
Version: 0.0.4
Summary: Deep Learning helpers and mlflow integration
Home-page: https://github.com/kleysonr/snsdl
Author: Kleyson Rios
Author-email: kleysonr@gmail.com
License: UNKNOWN
Platform: UNKNOWN
